{
  "schemaVersion": 1,
  "kind": "riftreader-current-truth",
  "updatedAtUtc": "2026-05-14T21:42:09.699992Z",
  "status": "current_target_pid23496_coordinate_proof_restored",
  "target": {
    "processName": "rift_x64",
    "processId": 23496,
    "targetWindowHandle": "0x2C1024",
    "windowTitle": "RIFT",
    "processStartUtc": "2026-05-14T20:02:28.245722Z",
    "moduleBase": "0x7FF71CD90000",
    "live": true,
    "status": "current-target-proofonly-passed",
    "lastVerifiedUtc": "2026-05-14T21:42:09.699992+00:00",
    "verificationSource": "docs/recovery/current-proof-anchor-readback.json + C:\\RIFT MODDING\\RiftReader\\scripts\\captures\\do-1-8-pid23496-proofonly-20260514-174113\\live-test-ProofOnly-20260514-214114\\run-summary.json",
    "lastClosedTargetEpoch": {
      "processName": "rift_x64",
      "processId": 16536,
      "targetWindowHandle": "0x1E0D66",
      "windowTitle": "RIFT",
      "processStartUtc": "2026-05-14T14:10:35.2003782Z",
      "moduleBase": "0x7FF71CD90000",
      "lastVerifiedUtc": "2026-05-14T18:36:23Z",
      "verificationSource": "Get-Process PID 16536 plus latest same-target ProofOnly artifacts"
    }
  },
  "liveReferenceSurface": {
    "authoritative": true,
    "status": "current-proof-anchor-readback",
    "source": "same-PID/HWND no-CE multi-pose proof anchor plus same-target ProofOnly",
    "view": "ProofOnly current proof-anchor readback for exact PID 23496 / HWND 0x2C1024",
    "savedVariablesUse": "none",
    "currentCoordinate": {
      "x": 7312.89453125,
      "y": 875.28466796875,
      "z": 3050.156005859375,
      "recordedAtUtc": "2026-05-14T21:42:09.0269307Z"
    },
    "latestProofOnlyStatus": "passed-proof-only",
    "latestProofOnlyGeneratedAtUtc": "2026-05-14T21:42:09.695159+00:00",
    "noCheatEngine": true,
    "movementSentByLatestProofOnly": false,
    "proofOnlyRunSummary": "C:\\RIFT MODDING\\RiftReader\\scripts\\captures\\do-1-8-pid23496-proofonly-20260514-174113\\live-test-ProofOnly-20260514-214114\\run-summary.json",
    "readbackSummaryFile": "C:\\RIFT MODDING\\RiftReader\\scripts\\captures\\proof-anchor-currentpid-23496-readback-summary-20260514-174203.json"
  },
  "movementGate": {
    "allowed": true,
    "status": "satisfied-by-current-process-proof-anchor-and-proofonly",
    "reason": "PID 23496 / HWND 0x2C1024 has a same-PID/HWND no-CE multi-pose proof anchor and same-target ProofOnly passed with movementSent=false.",
    "proofArtifact": "docs/recovery/current-proof-anchor-readback.json",
    "proofOnlyRunSummary": "C:\\RIFT MODDING\\RiftReader\\scripts\\captures\\do-1-8-pid23496-proofonly-20260514-174113\\live-test-ProofOnly-20260514-214114\\run-summary.json",
    "readbackSummary": "C:\\RIFT MODDING\\RiftReader\\scripts\\captures\\proof-anchor-currentpid-23496-readback-summary-20260514-174203.json",
    "movementSentByLatestProofOnly": false,
    "perRunRequirements": [
      "exact PID/HWND target-control",
      "fresh proof-anchor/readback age gate",
      "profile-specific input safety gate before any movement profile"
    ]
  },
  "bestCurrentCandidate": {
    "candidateId": "api-family-hit-000005",
    "addressHex": "0x27236F46750",
    "candidateFile": "C:\\RIFT MODDING\\RiftReader\\scripts\\captures\\family-scan-currentpid-23496-20260514-204452-232834\\api-family-vec3-candidates.json",
    "candidateFileJsonl": "C:\\RIFT MODDING\\RiftReader\\scripts\\captures\\family-scan-currentpid-23496-20260514-204452-232834\\api-family-vec3-candidates.jsonl",
    "status": "current_proof_anchor_promoted",
    "axisOrder": "xyz",
    "sourceBaseAddressHex": "0x27236F46710",
    "sourceOffsetHex": "0x40",
    "sourceAbsoluteAddressHex": "0x27236F46750",
    "supportCount": 4,
    "proofSupportCount": 4,
    "bestMaxAbsDistance": 0.007873437499256397,
    "promotedByProofAnchor": true,
    "proofAnchorFile": "C:\\RIFT MODDING\\RiftReader\\scripts\\captures\\telemetry-proof-coord-anchor.json",
    "movementGradeOnlyThroughCurrentProof": true,
    "validation_status": "same-target-proofonly-passed",
    "displacementProof": {
      "poseCount": 2,
      "maxReferencePlanarDisplacement": 4.285970374371978,
      "maxDeltaError": 0.006023046874815918,
      "readbackSummaries": [
        "scripts/captures/fast-proof-lane-pid23496-promote-poses-20260514-1650/riftscan-proof-poseA-displaced1-20260514-205119/riftscan-riftreader-currentpid-23496-readback-wrapper-summary-20260514-165156.json",
        "scripts/captures/fast-proof-lane-pid23496-promote-poses-20260514-1650/riftscan-proof-poseB-displaced2-20260514-205249/riftscan-riftreader-currentpid-23496-readback-wrapper-summary-20260514-165322.json"
      ]
    },
    "readbackSummary": "C:\\RIFT MODDING\\RiftReader\\scripts\\captures\\proof-anchor-currentpid-23496-readback-summary-20260514-174203.json"
  },
  "latestPointerEvidence": {
    "currentProofPointer": "docs/recovery/current-proof-anchor-readback.json",
    "status": "current-target-proofonly-passed",
    "lastUpdatedUtc": "2026-05-14T21:42:09.699992+00:00",
    "latestValidationStatus": "valid",
    "latestValidationGeneratedAtUtc": "2026-05-14T21:42:09.4266327+00:00",
    "latestProofOnlyStatus": "passed-proof-only",
    "latestProofOnlyGeneratedAtUtc": "2026-05-14T21:42:09.695159+00:00",
    "proofAnchorCandidateId": "api-family-hit-000005",
    "proofAnchorCandidateAddressHex": "0x27236F46750",
    "movementAllowed": true,
    "movementSent": false,
    "noCheatEngine": true,
    "proofOnlyRunSummary": "C:\\RIFT MODDING\\RiftReader\\scripts\\captures\\do-1-8-pid23496-proofonly-20260514-174113\\live-test-ProofOnly-20260514-214114\\run-summary.json",
    "readbackSummary": "C:\\RIFT MODDING\\RiftReader\\scripts\\captures\\proof-anchor-currentpid-23496-readback-summary-20260514-174203.json",
    "proofAnchorFile": "C:\\RIFT MODDING\\RiftReader\\scripts\\captures\\telemetry-proof-coord-anchor.json",
    "candidateFile": "C:\\RIFT MODDING\\RiftReader\\scripts\\captures\\family-scan-currentpid-23496-20260514-204452-232834\\api-family-vec3-candidates.json",
    "candidateFileJsonl": "C:\\RIFT MODDING\\RiftReader\\scripts\\captures\\family-scan-currentpid-23496-20260514-204452-232834\\api-family-vec3-candidates.jsonl"
  },
  "staleOrInvalid": [
    {
      "item": "PID 16536 / HWND 0x1E0D66 coordinate proof pointer",
      "status": "historical-stale-game-closed-after-x64dbg-access-capture",
      "reason": "The game was closed after x64dbg access proof capture and logout/close-only screen. Absolute address 0x21487DF8F64 is no longer a live movement truth surface.",
      "priorBestCandidate": "snapshot-delta-21487DF8F64-xyz at 0x21487DF8F64",
      "priorTruthStatus": "same-target ProofOnly passed before logout/close; stale after game close",
      "reusePolicy": "recovery evidence only; do not use for movement or current coordinate truth until a new in-world PID/HWND passes ProofOnly",
      "archiveMarkdown": "docs/recovery/historical/current-truth-2026-05-14-pid16536-hwnd1E0D66-closed-after-x64dbg.md",
      "archiveJson": "docs/recovery/historical/current-truth-2026-05-14-pid16536-hwnd1E0D66-closed-after-x64dbg.json",
      "historicalProofPointerArchive": "docs/recovery/historical/current-proof-anchor-readback-2026-05-14-pid16536-hwnd1E0D66-closed-after-x64dbg.json",
      "x64dbgAccessProof": {
        "status": "captured-before-close",
        "rawCaptureSummary": "scripts/captures/owner-access-path-21487DF8F64-currentpid-16536-hw-read-retry-after-rifterrorhandler/summary.json",
        "decodedAccessSummaryJson": "scripts/captures/owner-access-path-21487DF8F64-currentpid-16536-decoded-access-20260514-1956/decoded-access-summary.json",
        "decodedAccessSummaryMarkdown": "scripts/captures/owner-access-path-21487DF8F64-currentpid-16536-decoded-access-20260514-1956/decoded-access-summary.md",
        "accessInstruction": "rift_x64.exe+0x678A79: movsd qword ptr [rax+0xC4], xmm0",
        "componentBaseAtHit": "0x21487DF8EA0",
        "registers": {
          "base": "rax/rbx",
          "sourceCandidate": "rdi"
        },
        "xyzOffsetsFromComponentBase": {
          "x": "0xC4",
          "y": "0xC8",
          "z": "0xCC"
        },
        "sourceContextCandidate": {
          "register": "rdi",
          "valueAtHit": "0x214E38B5A00"
        },
        "classification": "access-proof-evidence-only-after-game-close; not live movement truth"
      }
    },
    {
      "item": "PID 2928 / HWND 0xC0994 current-truth state",
      "status": "historical-stale-target-epoch",
      "reason": "Superseded by PID 16536 / HWND 0x1E0D66 same-target ProofOnly proof pointer.",
      "priorBestCandidate": "api-family-hit-000001 at 0x268E2BC09E0",
      "priorTruthStatus": "candidate-only / displacement-gate-blocked / movement-blocked",
      "reusePolicy": "audit and broad family-history context only; do not use as current coordinate proof or movement truth",
      "archiveMarkdown": "docs/recovery/historical/current-truth-2026-05-14-pid2928-hwndC0994-historical.md",
      "archiveJson": "docs/recovery/historical/current-truth-2026-05-14-pid2928-hwndC0994-historical.json",
      "historicalProofPointerArchive": "docs/recovery/historical/current-proof-anchor-readback-2026-05-14-pid2928-hwndC0994-historical.json"
    },
    {
      "item": "SavedVariables coordinates",
      "status": "not-live-truth",
      "reason": "SavedVariables are post-save snapshots only and were not used for the PID 16536 promotion."
    },
    {
      "item": "Older absolute proof/candidate addresses from PID 2928 and earlier epochs",
      "status": "historical-only",
      "reason": "Absolute addresses are target-epoch-specific and must be rescored after PID/HWND drift."
    }
  ],
  "currentBlockers": [
    "No active coordinate-proof blocker after PID23496 ProofOnly pass; movement still requires exact per-run target/proof-age/input safety gates.",
    "Anchor api-family-hit-000005 @ 0x27236F46750 is valid only for current PID 23496 / HWND 0x2C1024 epoch.",
    "Do not reuse stale PID16536 address 0x21487DF8F64 as live truth.",
    "Owner/static-chain provenance remains unresolved and is deferred unless the fast proof lane fails."
  ],
  "canonicalArtifacts": {
    "currentTruthMarkdown": "docs/recovery/current-truth.md",
    "currentTruthJson": "docs/recovery/current-truth.json",
    "currentProofPointer": "docs/recovery/current-proof-anchor-readback.json",
    "currentHandoff": "docs/handoffs/2026-05-14-1711-current-pid-coordinate-proof-restored.md",
    "historicalPid2928CurrentTruthMarkdown": "docs/recovery/historical/current-truth-2026-05-14-pid2928-hwndC0994-historical.md",
    "historicalPid2928CurrentTruthJson": "docs/recovery/historical/current-truth-2026-05-14-pid2928-hwndC0994-historical.json",
    "historicalPid2928ProofPointer": "docs/recovery/historical/current-proof-anchor-readback-2026-05-14-pid2928-hwndC0994-historical.json",
    "proofOnlyRunSummary": "C:\\RIFT MODDING\\RiftReader\\scripts\\captures\\do-1-8-pid23496-proofonly-20260514-174113\\live-test-ProofOnly-20260514-214114\\run-summary.json",
    "proofOnlyTargetControl": "C:\\RIFT MODDING\\RiftReader\\scripts\\captures\\do-1-8-pid23496-proofonly-20260514-174113\\live-test-ProofOnly-20260514-214114\\target-control\\target-control-status.json",
    "proofAnchorReadbackSummary": "C:\\RIFT MODDING\\RiftReader\\scripts\\captures\\proof-anchor-currentpid-23496-readback-summary-20260514-174203.json",
    "proofAnchorCache": "C:\\RIFT MODDING\\RiftReader\\scripts\\captures\\telemetry-proof-coord-anchor.json",
    "candidateFile": "C:\\RIFT MODDING\\RiftReader\\scripts\\captures\\family-scan-currentpid-23496-20260514-204452-232834\\api-family-vec3-candidates.json",
    "candidateFileJsonl": "C:\\RIFT MODDING\\RiftReader\\scripts\\captures\\family-scan-currentpid-23496-20260514-204452-232834\\api-family-vec3-candidates.jsonl",
    "deltaSummary": "scripts/captures/family-snapshot-sequence-currentpid-16536-live-approved-threepose-20260514-122550-422022/delta-analysis/delta-summary.json",
    "familySnapshotSummary": "scripts/captures/family-snapshot-sequence-currentpid-16536-live-approved-threepose-20260514-122550-422022/summary.json",
    "coordinateProofRoute": "scripts/captures/coordinate-proof-route-20260514-163509-016518/coordinate-proof-route.json",
    "promotionBatchSummary": "scripts/captures/current-pid-coordinate-anchor-batch-16536-live-approved-route-20260514-163620/coordinate-anchor-batch-summary.json",
    "priorForward250Smoke": "scripts/captures/live-test-Forward250-20260514-164220/run-summary.json",
    "riftscanMilestoneReview": "scripts/captures/riftscan-milestone-review-20260514-171113.json",
    "currentDiscoveryHtml": "docs/recovery/current-pid-coordinate-proof-anchor-discovery-2026-05-14.html",
    "currentDiscoveryMarkdown": "docs/recovery/current-pid-coordinate-proof-anchor-discovery-2026-05-14.md",
    "historicalTimelineHtml": "docs/recovery/historical-coordinate-proof-anchor-discovery-timelines-2026-05.html",
    "historicalTimelineMarkdown": "docs/recovery/historical-coordinate-proof-anchor-discovery-timelines-2026-05.md",
    "historicalTimelineMachineMarkdown": "docs/recovery/historical-coordinate-proof-anchor-discovery-timelines-2026-05.machine.md",
    "historicalPid16536CurrentTruthMarkdown": "docs/recovery/historical/current-truth-2026-05-14-pid16536-hwnd1E0D66-closed-after-x64dbg.md",
    "historicalPid16536CurrentTruthJson": "docs/recovery/historical/current-truth-2026-05-14-pid16536-hwnd1E0D66-closed-after-x64dbg.json",
    "historicalPid16536ProofPointer": "docs/recovery/historical/current-proof-anchor-readback-2026-05-14-pid16536-hwnd1E0D66-closed-after-x64dbg.json",
    "logoutAfterX64dbgMarker": "scripts/captures/logout-after-x64dbg-capture-20260514-1959/logout-after-x64dbg-capture-summary.json",
    "x64dbgAccessProofDecoded": "scripts/captures/owner-access-path-21487DF8F64-currentpid-16536-decoded-access-20260514-1956/decoded-access-summary.json",
    "x64dbgAccessProofRaw": "scripts/captures/owner-access-path-21487DF8F64-currentpid-16536-hw-read-retry-after-rifterrorhandler/summary.json",
    "postCloseTargetDiscovery": "scripts/captures/post-close-target-discovery-20260514-2004/target-control-status.json",
    "postCloseCurrentTargetPreflight": "scripts/captures/x64dbg-target-preflight-20260514-200725-524137/summary.json",
    "postCloseCurrentTargetProofOnlyBlocked": "scripts/captures/post-close-proofonly-current-target-23496-20260514-2007/live-test-ProofOnly-20260514-200725/run-summary.json",
    "familyScanSummary": "C:\\RIFT MODDING\\RiftReader\\scripts\\captures\\family-scan-currentpid-23496-20260514-204452-232834\\family-scan-summary.json"
  },
  "nextRecommendedAction": "Coordinate proof remains restored for PID 23496/HWND 0x2C1024 after fresh target-control and ProofOnly. Before movement, rerun exact target-control/proof-age gates; defer x64dbg/static-chain unless the fast proof lane fails.",
  "historicalState": {
    "pid2928": {
      "status": "historical_stale",
      "target": {
        "processName": "rift_x64",
        "processId": 2928,
        "targetWindowHandle": "0xC0994",
        "processStartUtc": "2026-05-13T16:17:56.208370Z",
        "moduleBase": "0x7FF71CD90000"
      },
      "lastKnownVerdict": "read-only API-memory candidate only; displacement-gated promotion blocked; movement blocked",
      "priorBestCandidate": {
        "candidateId": "api-family-hit-000001",
        "addressHex": "0x268E2BC09E0",
        "candidateFile": "scripts/captures/family-scan-currentpid-2928-20260514-114535-319032/api-family-vec3-candidates.jsonl",
        "readbackSummary": "scripts/captures/riftscan-proof-readonly-fresh-displaced-attempt-1-20260514-120812/riftscan-riftreader-currentpid-2928-readback-wrapper-summary-20260514-080850.json",
        "referenceFile": "scripts/captures/riftscan-proof-readonly-fresh-displaced-attempt-1-20260514-120812/readonly-fresh-displaced-attempt-1-api-reference.json",
        "referenceCoordinate": {
          "x": 7399.109863,
          "y": 871.769958,
          "z": 3029.959961,
          "capturedAtUtc": "2026-05-14T12:08:49.0014728Z"
        },
        "referenceMatchCount": 1,
        "stableDecodedCandidateCount": 2,
        "referenceMaxAbsDelta": 4.960937758369255e-07,
        "status": "same_pose_api_memory_match_candidate_displacement_gate_blocked",
        "whySelected": "Latest route-selected candidate remains the freshest API-memory-match candidate, but displacement-gated comparison proves the second reference was not a valid moved pose.",
        "notMovementProofBecause": [
          "promotion-two-reference-candidate-match-missing",
          "promotion-displaced-readiness-not-passed:blocked",
          "displaced-api-reference-planar-distance-too-small:5.37587e-05<1.0",
          "displaced-reference-age-exceeded:1363.884>300.0",
          "displaced-reference-planar-distance-too-small:5.6e-05<1.0",
          "route-valid-both-reference-count=0-after-displacement-gate",
          "movement remains blocked until true displaced proof/static proof/same-target ProofOnly/explicit approval"
        ]
      },
      "priorMovementGate": {
        "allowed": false,
        "status": "blocked",
        "reason": "Same-pose API-memory match remains usable for read-only proof planning, but displacement-gated comparison has valid both-reference count 0; no promotion or movement proof.",
        "requiredBeforeMovement": [
          "fresh API/runtime reference",
          "current-process memory candidate agreement across poses",
          "current proof anchor or static chain",
          "same-target ProofOnly pass",
          "explicit approval for movement/player-control input"
        ]
      },
      "archiveMarkdown": "docs/recovery/historical/current-truth-2026-05-14-pid2928-hwndC0994-historical.md",
      "archiveJson": "docs/recovery/historical/current-truth-2026-05-14-pid2928-hwndC0994-historical.json",
      "historicalProofPointerArchive": "docs/recovery/historical/current-proof-anchor-readback-2026-05-14-pid2928-hwndC0994-historical.json"
    }
  },
  "liveTestingBoundary": {
    "status": "coordinate_proof_gate_satisfied_current_pid",
    "updatedAtUtc": "2026-05-14T21:42:09.699992Z",
    "readOnlyLiveTestingAllowed": true,
    "coordinateProofMovementGateAllowed": true,
    "latestProofOnlyMovementSent": false,
    "playerControlStillRequiresPerRunSafetyGate": true,
    "noCheatEngine": true,
    "savedVariablesLiveTruthAllowed": false,
    "blockedActionsWithoutFreshExplicitApproval": [
      "x64dbg attach/static-chain work unless the fast proof lane fails",
      "using stale PID 16536 or PID 2928 candidates as current proof",
      "using absolute address 0x21487DF8F64 as current movement truth after process restart"
    ]
  },
  "nativeScreenshotKeybind": {
    "status": "verified_working_for_local_rift_installation",
    "verifiedAtUtc": "2026-05-14T05:49:34Z",
    "action": "Take Screenshot",
    "currentKeybind": "NUM PAD *",
    "normalizedKeyChord": "numpad_multiply",
    "virtualKey": "0x6A",
    "virtualKeyName": "VK_MULTIPLY",
    "keybindSource": "C:\\Program Files (x86)\\Glyph\\Games\\RIFT\\Live\\mykeybindings",
    "keybindSourceLastWriteLocal": "2026-05-14T01:39:32-04:00",
    "actionId": 20010,
    "exportedRecordHex": "02 6A 07 AA 9C 01",
    "defaultRecordHex": "02 2C 07 AA 9C 01",
    "defaultKey": "PrintScreen / VK_SNAPSHOT / 0x2C",
    "currentLocalInstallKey": "NUM PAD * / VK_MULTIPLY / 0x6A",
    "verificationTarget": {
      "processName": "rift_x64",
      "processId": 2928,
      "targetWindowHandle": "0xC0994",
      "windowTitle": "RIFT"
    },
    "createdScreenshot": "C:\\Users\\mrkoo\\OneDrive\\Documents\\RIFT\\Screenshots\\2026-05-14_014934.jpg",
    "createdScreenshotLastWriteUtc": "2026-05-14T05:49:34.447128+00:00",
    "repoProofPacket": "scripts/captures/native-screenshot-keybind-20260514-014933/native-screenshot-result.json",
    "repoArtifactCopy": "scripts/captures/native-screenshot-keybind-20260514-014933/rift-native-numpad-multiply-screenshot-20260514-054934.jpg",
    "forbiddenKeys": [
      "Ctrl+P",
      "Control+P",
      "PrintScreen",
      "Win+Shift+S automation"
    ],
    "truthScope": "visual_screenshot_evidence_only_not_coordinate_or_movement_truth",
    "safety": {
      "movementSent": false,
      "cheatEngineUsed": false,
      "x64dbgUsed": false,
      "reloadUiSent": false,
      "providerWrites": false
    },
    "coordinateProofRelevance": "not-coordinate-proof; retained because the local keybind remains a useful visual-evidence fact"
  },
  "visualEvidenceRouting": {
    "status": "sidecar_only_not_coordinate_or_movement_truth",
    "visualEvidenceCanPromoteTruth": false,
    "notes": [
      "Coordinate proof truth is currently restored for active PID 23496 / HWND 0x2C1024 by same-target proof pointer and ProofOnly.",
      "PID 16536 proof-pointer/readback evidence is historical after game close and cannot be used as movement truth.",
      "The local screenshot keybind remains visual evidence only."
    ]
  },
  "closedEvent": {
    "status": "game-closed-by-operator-after-x64dbg-access-capture",
    "reportedAtUtc": "2026-05-14T20:04:04Z",
    "reportedByOperator": "i closed the game",
    "processObservedAfterClose": "no rift_x64/RIFT process listed by Get-Process filter",
    "priorLogoutMarker": "scripts/captures/logout-after-x64dbg-capture-20260514-1959/logout-after-x64dbg-capture-summary.json",
    "reasonTruthIsStale": "The RIFT process/client epoch is closed. Absolute addresses from PID 16536 are no longer live player actor coordinate truth."
  }
}
