{
  "Mode": "capture-consistency-report",
  "Root": "C:\\RIFT MODDING\\RiftReader\\scripts\\captures",
  "GeneratedAtUtc": "2026-04-13T18:04:17.5194482+00:00",
  "FileCount": 44,
  "ParsedCount": 44,
  "WarningCount": 30,
  "Records": [
    {
      "FileName": "actor-orientation-key-profile.json",
      "Mode": "actor-orientation-key-profile",
      "GeneratedAtUtc": "2026-04-09T02:26:22.0000000-04:00",
      "LoadedAtUtc": null,
      "ProcessName": "n/a",
      "ProcessId": null,
      "SourceFile": "n/a",
      "SelectorTraceFile": "n/a",
      "FamilyId": "n/a",
      "Signature": "n/a",
      "SelectionSource": "n/a",
      "OwnerAddress": null,
      "ContainerAddress": null,
      "SelectedSourceAddress": null,
      "StateRecordAddress": null,
      "SelectedEntryAddress": null,
      "SourceObjectAddress": null,
      "Warnings": [
        "no selected source or source object anchor found"
      ]
    },
    {
      "FileName": "auto-camera-alts-diff.json",
      "Mode": "auto-camera-alts-diff",
      "GeneratedAtUtc": "2026-04-13T02:40:41.0000000-04:00",
      "LoadedAtUtc": null,
      "ProcessName": "n/a",
      "ProcessId": null,
      "SourceFile": "n/a",
      "SelectorTraceFile": "n/a",
      "FamilyId": "n/a",
      "Signature": "n/a",
      "SelectionSource": "n/a",
      "OwnerAddress": null,
      "ContainerAddress": null,
      "SelectedSourceAddress": null,
      "StateRecordAddress": null,
      "SelectedEntryAddress": null,
      "SourceObjectAddress": null,
      "Warnings": [
        "no selected source or source object anchor found"
      ]
    },
    {
      "FileName": "camera-alts-stimulus-safe.json",
      "Mode": "camera-alts-stimulus-safe",
      "GeneratedAtUtc": "2026-04-13T03:50:57.0000000-04:00",
      "LoadedAtUtc": null,
      "ProcessName": "n/a",
      "ProcessId": null,
      "SourceFile": "n/a",
      "SelectorTraceFile": "n/a",
      "FamilyId": "n/a",
      "Signature": "n/a",
      "SelectionSource": "n/a",
      "OwnerAddress": "0X1576A38AA10",
      "ContainerAddress": "0X1577AD9B540",
      "SelectedSourceAddress": "0X1577AC2FB60",
      "StateRecordAddress": null,
      "SelectedEntryAddress": null,
      "SourceObjectAddress": "0X1577AC2FB60",
      "Warnings": []
    },
    {
      "FileName": "camera-alts-stimulus.json",
      "Mode": "camera-alts-stimulus",
      "GeneratedAtUtc": "2026-04-13T02:13:30.0000000-04:00",
      "LoadedAtUtc": null,
      "ProcessName": "n/a",
      "ProcessId": null,
      "SourceFile": "n/a",
      "SelectorTraceFile": "n/a",
      "FamilyId": "n/a",
      "Signature": "n/a",
      "SelectionSource": "n/a",
      "OwnerAddress": "0X1576A38AA10",
      "ContainerAddress": "0X1577AD9B540",
      "SelectedSourceAddress": "0X1577AC2FB60",
      "StateRecordAddress": null,
      "SelectedEntryAddress": null,
      "SourceObjectAddress": "0X1577AC2FB60",
      "Warnings": []
    },
    {
      "FileName": "camera-altz-stimulus-safe.json",
      "Mode": "camera-altz-stimulus-safe",
      "GeneratedAtUtc": "2026-04-13T04:00:13.0000000-04:00",
      "LoadedAtUtc": null,
      "ProcessName": "n/a",
      "ProcessId": null,
      "SourceFile": "n/a",
      "SelectorTraceFile": "n/a",
      "FamilyId": "n/a",
      "Signature": "n/a",
      "SelectionSource": "n/a",
      "OwnerAddress": "0X1576A38AA10",
      "ContainerAddress": "0X1577AD9B540",
      "SelectedSourceAddress": "0X1577AC2FB60",
      "StateRecordAddress": null,
      "SelectedEntryAddress": null,
      "SourceObjectAddress": "0X1577AC2FB60",
      "Warnings": []
    },
    {
      "FileName": "camera-altz-stimulus.json",
      "Mode": "camera-altz-stimulus",
      "GeneratedAtUtc": "2026-04-13T02:14:01.0000000-04:00",
      "LoadedAtUtc": null,
      "ProcessName": "n/a",
      "ProcessId": null,
      "SourceFile": "n/a",
      "SelectorTraceFile": "n/a",
      "FamilyId": "n/a",
      "Signature": "n/a",
      "SelectionSource": "n/a",
      "OwnerAddress": "0X1576A38AA10",
      "ContainerAddress": "0X1577AD9B540",
      "SelectedSourceAddress": "0X1577AC2FB60",
      "StateRecordAddress": null,
      "SelectedEntryAddress": null,
      "SourceObjectAddress": "0X1577AC2FB60",
      "Warnings": []
    },
    {
      "FileName": "camera-yaw-candidates.json",
      "Mode": "ce-smart-camera-yaw",
      "GeneratedAtUtc": "2026-04-13T07:47:29.0000000-04:00",
      "LoadedAtUtc": null,
      "ProcessName": "rift_x64",
      "ProcessId": null,
      "SourceFile": "n/a",
      "SelectorTraceFile": "n/a",
      "FamilyId": "n/a",
      "Signature": "n/a",
      "SelectionSource": "n/a",
      "OwnerAddress": null,
      "ContainerAddress": null,
      "SelectedSourceAddress": null,
      "StateRecordAddress": null,
      "SelectedEntryAddress": null,
      "SourceObjectAddress": null,
      "Warnings": [
        "no selected source or source object anchor found"
      ]
    },
    {
      "FileName": "ce-family-neighborhood.json",
      "Mode": "ce-family-neighborhood",
      "GeneratedAtUtc": "2026-04-10T08:21:39.0000000-04:00",
      "LoadedAtUtc": null,
      "ProcessName": "n/a",
      "ProcessId": null,
      "SourceFile": "n/a",
      "SelectorTraceFile": "n/a",
      "FamilyId": "n/a",
      "Signature": "n/a",
      "SelectionSource": "n/a",
      "OwnerAddress": null,
      "ContainerAddress": null,
      "SelectedSourceAddress": "0X1577AC2FB60",
      "StateRecordAddress": null,
      "SelectedEntryAddress": null,
      "SourceObjectAddress": "0X1577AC2FB60",
      "Warnings": []
    },
    {
      "FileName": "ce-smart-player-family.json",
      "Mode": "ce-smart-player-family",
      "GeneratedAtUtc": "2026-04-10T08:20:32.0000000-04:00",
      "LoadedAtUtc": null,
      "ProcessName": "rift_x64",
      "ProcessId": null,
      "SourceFile": "n/a",
      "SelectorTraceFile": "n/a",
      "FamilyId": "n/a",
      "Signature": "n/a",
      "SelectionSource": "n/a",
      "OwnerAddress": null,
      "ContainerAddress": null,
      "SelectedSourceAddress": null,
      "StateRecordAddress": null,
      "SelectedEntryAddress": null,
      "SourceObjectAddress": null,
      "Warnings": [
        "no selected source or source object anchor found"
      ]
    },
    {
      "FileName": "deep-scan-entry15.json",
      "Mode": "deep-scan-entry15",
      "GeneratedAtUtc": "2026-04-10T16:51:30.0000000-04:00",
      "LoadedAtUtc": null,
      "ProcessName": "n/a",
      "ProcessId": null,
      "SourceFile": "n/a",
      "SelectorTraceFile": "n/a",
      "FamilyId": "n/a",
      "Signature": "n/a",
      "SelectionSource": "n/a",
      "OwnerAddress": null,
      "ContainerAddress": null,
      "SelectedSourceAddress": null,
      "StateRecordAddress": null,
      "SelectedEntryAddress": null,
      "SourceObjectAddress": null,
      "Warnings": [
        "no selected source or source object anchor found"
      ]
    },
    {
      "FileName": "hotspot-15788C21-after-idle.json",
      "Mode": "n/a",
      "GeneratedAtUtc": "2026-04-11T13:13:28.0000000-04:00",
      "LoadedAtUtc": null,
      "ProcessName": "n/a",
      "ProcessId": null,
      "SourceFile": "n/a",
      "SelectorTraceFile": "n/a",
      "FamilyId": "n/a",
      "Signature": "n/a",
      "SelectionSource": "n/a",
      "OwnerAddress": null,
      "ContainerAddress": null,
      "SelectedSourceAddress": null,
      "StateRecordAddress": null,
      "SelectedEntryAddress": null,
      "SourceObjectAddress": null,
      "Warnings": [
        "no selected source or source object anchor found"
      ]
    },
    {
      "FileName": "hotspot-15788C21-after-pitch.json",
      "Mode": "n/a",
      "GeneratedAtUtc": "2026-04-11T13:14:21.0000000-04:00",
      "LoadedAtUtc": null,
      "ProcessName": "n/a",
      "ProcessId": null,
      "SourceFile": "n/a",
      "SelectorTraceFile": "n/a",
      "FamilyId": "n/a",
      "Signature": "n/a",
      "SelectionSource": "n/a",
      "OwnerAddress": null,
      "ContainerAddress": null,
      "SelectedSourceAddress": null,
      "StateRecordAddress": null,
      "SelectedEntryAddress": null,
      "SourceObjectAddress": null,
      "Warnings": [
        "no selected source or source object anchor found"
      ]
    },
    {
      "FileName": "hotspot-15788C21-after-yaw.json",
      "Mode": "n/a",
      "GeneratedAtUtc": "2026-04-11T13:12:56.0000000-04:00",
      "LoadedAtUtc": null,
      "ProcessName": "n/a",
      "ProcessId": null,
      "SourceFile": "n/a",
      "SelectorTraceFile": "n/a",
      "FamilyId": "n/a",
      "Signature": "n/a",
      "SelectionSource": "n/a",
      "OwnerAddress": null,
      "ContainerAddress": null,
      "SelectedSourceAddress": null,
      "StateRecordAddress": null,
      "SelectedEntryAddress": null,
      "SourceObjectAddress": null,
      "Warnings": [
        "no selected source or source object anchor found"
      ]
    },
    {
      "FileName": "hotspot-15788C21-baseline.json",
      "Mode": "n/a",
      "GeneratedAtUtc": "2026-04-11T13:11:47.0000000-04:00",
      "LoadedAtUtc": null,
      "ProcessName": "n/a",
      "ProcessId": null,
      "SourceFile": "n/a",
      "SelectorTraceFile": "n/a",
      "FamilyId": "n/a",
      "Signature": "n/a",
      "SelectionSource": "n/a",
      "OwnerAddress": null,
      "ContainerAddress": null,
      "SelectedSourceAddress": null,
      "StateRecordAddress": null,
      "SelectedEntryAddress": null,
      "SourceObjectAddress": null,
      "Warnings": [
        "no selected source or source object anchor found"
      ]
    },
    {
      "FileName": "hotspot-15788C21-before-idle.json",
      "Mode": "n/a",
      "GeneratedAtUtc": "2026-04-11T13:13:26.0000000-04:00",
      "LoadedAtUtc": null,
      "ProcessName": "n/a",
      "ProcessId": null,
      "SourceFile": "n/a",
      "SelectorTraceFile": "n/a",
      "FamilyId": "n/a",
      "Signature": "n/a",
      "SelectionSource": "n/a",
      "OwnerAddress": null,
      "ContainerAddress": null,
      "SelectedSourceAddress": null,
      "StateRecordAddress": null,
      "SelectedEntryAddress": null,
      "SourceObjectAddress": null,
      "Warnings": [
        "no selected source or source object anchor found"
      ]
    },
    {
      "FileName": "hotspot-15788C21-before-pitch.json",
      "Mode": "n/a",
      "GeneratedAtUtc": "2026-04-11T13:14:03.0000000-04:00",
      "LoadedAtUtc": null,
      "ProcessName": "n/a",
      "ProcessId": null,
      "SourceFile": "n/a",
      "SelectorTraceFile": "n/a",
      "FamilyId": "n/a",
      "Signature": "n/a",
      "SelectionSource": "n/a",
      "OwnerAddress": null,
      "ContainerAddress": null,
      "SelectedSourceAddress": null,
      "StateRecordAddress": null,
      "SelectedEntryAddress": null,
      "SourceObjectAddress": null,
      "Warnings": [
        "no selected source or source object anchor found"
      ]
    },
    {
      "FileName": "hotspot-15788C21-before-yaw.json",
      "Mode": "n/a",
      "GeneratedAtUtc": "2026-04-11T13:12:22.0000000-04:00",
      "LoadedAtUtc": null,
      "ProcessName": "n/a",
      "ProcessId": null,
      "SourceFile": "n/a",
      "SelectorTraceFile": "n/a",
      "FamilyId": "n/a",
      "Signature": "n/a",
      "SelectionSource": "n/a",
      "OwnerAddress": null,
      "ContainerAddress": null,
      "SelectedSourceAddress": null,
      "StateRecordAddress": null,
      "SelectedEntryAddress": null,
      "SourceObjectAddress": null,
      "Warnings": [
        "no selected source or source object anchor found"
      ]
    },
    {
      "FileName": "manual-camera-alts-diff.json",
      "Mode": "manual-camera-alts-diff",
      "GeneratedAtUtc": "2026-04-13T04:02:09.0000000-04:00",
      "LoadedAtUtc": null,
      "ProcessName": "n/a",
      "ProcessId": null,
      "SourceFile": "n/a",
      "SelectorTraceFile": "n/a",
      "FamilyId": "n/a",
      "Signature": "n/a",
      "SelectionSource": "n/a",
      "OwnerAddress": null,
      "ContainerAddress": null,
      "SelectedSourceAddress": null,
      "StateRecordAddress": null,
      "SelectedEntryAddress": null,
      "SourceObjectAddress": null,
      "Warnings": [
        "no selected source or source object anchor found"
      ]
    },
    {
      "FileName": "owner-state-neighborhood.json",
      "Mode": "owner-state-neighborhood",
      "GeneratedAtUtc": "2026-04-10T09:05:13.0000000-04:00",
      "LoadedAtUtc": null,
      "ProcessName": "n/a",
      "ProcessId": null,
      "SourceFile": "n/a",
      "SelectorTraceFile": "n/a",
      "FamilyId": "n/a",
      "Signature": "n/a",
      "SelectionSource": "n/a",
      "OwnerAddress": "0X1576A38AA10",
      "ContainerAddress": null,
      "SelectedSourceAddress": "0X1577AC2FB60",
      "StateRecordAddress": "0X1576A38AAD8",
      "SelectedEntryAddress": null,
      "SourceObjectAddress": null,
      "Warnings": []
    },
    {
      "FileName": "player-actor-orientation.json",
      "Mode": "player-actor-orientation-capture",
      "GeneratedAtUtc": "2026-04-09T02:26:35.0000000-04:00",
      "LoadedAtUtc": null,
      "ProcessName": "n/a",
      "ProcessId": null,
      "SourceFile": "n/a",
      "SelectorTraceFile": "n/a",
      "FamilyId": "n/a",
      "Signature": "n/a",
      "SelectionSource": "n/a",
      "OwnerAddress": null,
      "ContainerAddress": null,
      "SelectedSourceAddress": null,
      "StateRecordAddress": null,
      "SelectedEntryAddress": null,
      "SourceObjectAddress": null,
      "Warnings": [
        "no selected source or source object anchor found"
      ]
    },
    {
      "FileName": "player-coord-trace-cluster.json",
      "Mode": "player-coord-trace-cluster",
      "GeneratedAtUtc": "2026-04-10T08:22:05.0000000-04:00",
      "LoadedAtUtc": null,
      "ProcessName": "n/a",
      "ProcessId": null,
      "SourceFile": "C:\\RIFT MODDING\\RiftReader\\scripts\\captures\\player-coord-write-trace.json",
      "SelectorTraceFile": "C:\\RIFT MODDING\\RiftReader\\scripts\\captures\\player-coord-write-trace.json",
      "FamilyId": "n/a",
      "Signature": "n/a",
      "SelectionSource": "n/a",
      "OwnerAddress": null,
      "ContainerAddress": null,
      "SelectedSourceAddress": "0X1577AC2FB60",
      "StateRecordAddress": null,
      "SelectedEntryAddress": null,
      "SourceObjectAddress": "0X1577AC2FB60",
      "Warnings": []
    },
    {
      "FileName": "player-coord-write-trace.json",
      "Mode": "player-coord-write-trace",
      "GeneratedAtUtc": "2026-04-10T08:07:25.0000000-04:00",
      "LoadedAtUtc": null,
      "ProcessName": "rift_x64",
      "ProcessId": "98428",
      "SourceFile": "n/a",
      "SelectorTraceFile": "n/a",
      "FamilyId": "n/a",
      "Signature": "n/a",
      "SelectionSource": "n/a",
      "OwnerAddress": null,
      "ContainerAddress": null,
      "SelectedSourceAddress": "0X1577AC2FB60",
      "StateRecordAddress": null,
      "SelectedEntryAddress": null,
      "SourceObjectAddress": "0X1577AC2FB60",
      "Warnings": []
    },
    {
      "FileName": "player-current-anchor.json",
      "Mode": "n/a",
      "GeneratedAtUtc": "2026-04-13T13:52:48.0000000-04:00",
      "LoadedAtUtc": null,
      "ProcessName": "rift_x64",
      "ProcessId": null,
      "SourceFile": "n/a",
      "SelectorTraceFile": "n/a",
      "FamilyId": "fam-6F81F26E",
      "Signature": "level@-144|health[1]@-136|health[2]@-128|health[3]@-120|coords@0",
      "SelectionSource": "ce-guided-family",
      "OwnerAddress": null,
      "ContainerAddress": null,
      "SelectedSourceAddress": null,
      "StateRecordAddress": null,
      "SelectedEntryAddress": null,
      "SourceObjectAddress": null,
      "Warnings": [
        "no selected source or source object anchor found"
      ]
    },
    {
      "FileName": "player-owner-components.json",
      "Mode": "player-owner-components",
      "GeneratedAtUtc": "2026-04-10T03:03:33.0000000-04:00",
      "LoadedAtUtc": null,
      "ProcessName": "n/a",
      "ProcessId": null,
      "SourceFile": "C:\\RIFT MODDING\\RiftReader\\scripts\\captures\\player-selector-owner-trace.json",
      "SelectorTraceFile": "C:\\RIFT MODDING\\RiftReader\\scripts\\captures\\player-selector-owner-trace.json",
      "FamilyId": "n/a",
      "Signature": "n/a",
      "SelectionSource": "n/a",
      "OwnerAddress": "0X1576A38AA10",
      "ContainerAddress": "0X1577AD9B540",
      "SelectedSourceAddress": "0X1577AC2FB60",
      "StateRecordAddress": "0X1576A38AAD8",
      "SelectedEntryAddress": null,
      "SourceObjectAddress": null,
      "Warnings": []
    },
    {
      "FileName": "player-owner-graph.json",
      "Mode": "player-owner-graph",
      "GeneratedAtUtc": "2026-04-10T09:03:52.0000000-04:00",
      "LoadedAtUtc": null,
      "ProcessName": "n/a",
      "ProcessId": null,
      "SourceFile": "C:\\RIFT MODDING\\RiftReader\\scripts\\captures\\player-selector-owner-trace.json",
      "SelectorTraceFile": "C:\\RIFT MODDING\\RiftReader\\scripts\\captures\\player-selector-owner-trace.json",
      "FamilyId": "n/a",
      "Signature": "n/a",
      "SelectionSource": "n/a",
      "OwnerAddress": "0X1576A38AA10",
      "ContainerAddress": "0X1577AD9B540",
      "SelectedSourceAddress": "0X1577AC2FB60",
      "StateRecordAddress": null,
      "SelectedEntryAddress": null,
      "SourceObjectAddress": null,
      "Warnings": []
    },
    {
      "FileName": "player-selector-owner-trace.json",
      "Mode": "player-selector-owner-trace",
      "GeneratedAtUtc": "2026-04-11T13:41:56.0000000-04:00",
      "LoadedAtUtc": null,
      "ProcessName": "n/a",
      "ProcessId": null,
      "SourceFile": "n/a",
      "SelectorTraceFile": "C:\\RIFT MODDING\\RiftReader\\scripts\\captures\\player-source-chain.json",
      "FamilyId": "n/a",
      "Signature": "n/a",
      "SelectionSource": "n/a",
      "OwnerAddress": "0X2E19901B210",
      "ContainerAddress": "0X2E199188E60",
      "SelectedSourceAddress": "0X2E199183210",
      "StateRecordAddress": null,
      "SelectedEntryAddress": null,
      "SourceObjectAddress": null,
      "Warnings": []
    },
    {
      "FileName": "player-source-accessor-family.json",
      "Mode": "player-source-accessor-family",
      "GeneratedAtUtc": "2026-04-10T03:03:03.0000000-04:00",
      "LoadedAtUtc": null,
      "ProcessName": "n/a",
      "ProcessId": null,
      "SourceFile": "C:\\RIFT MODDING\\RiftReader\\scripts\\captures\\player-coord-write-trace.json",
      "SelectorTraceFile": "C:\\RIFT MODDING\\RiftReader\\scripts\\captures\\player-coord-write-trace.json",
      "FamilyId": "n/a",
      "Signature": "n/a",
      "SelectionSource": "n/a",
      "OwnerAddress": null,
      "ContainerAddress": null,
      "SelectedSourceAddress": "0X1577AC2FB60",
      "StateRecordAddress": null,
      "SelectedEntryAddress": null,
      "SourceObjectAddress": "0X1577AC2FB60",
      "Warnings": []
    },
    {
      "FileName": "player-source-chain.json",
      "Mode": "player-source-chain",
      "GeneratedAtUtc": "2026-04-10T08:16:21.0000000-04:00",
      "LoadedAtUtc": null,
      "ProcessName": "n/a",
      "ProcessId": null,
      "SourceFile": "C:\\RIFT MODDING\\RiftReader\\scripts\\captures\\player-coord-trace-cluster.json",
      "SelectorTraceFile": "C:\\RIFT MODDING\\RiftReader\\scripts\\captures\\player-coord-trace-cluster.json",
      "FamilyId": "n/a",
      "Signature": "n/a",
      "SelectionSource": "n/a",
      "OwnerAddress": null,
      "ContainerAddress": null,
      "SelectedSourceAddress": "0X1577AC2FB60",
      "StateRecordAddress": null,
      "SelectedEntryAddress": null,
      "SourceObjectAddress": "0X1577AC2FB60",
      "Warnings": []
    },
    {
      "FileName": "player-stat-component-candidates.json",
      "Mode": "player-stat-component-candidates",
      "GeneratedAtUtc": "2026-04-09T00:24:02.0000000-04:00",
      "LoadedAtUtc": null,
      "ProcessName": "n/a",
      "ProcessId": null,
      "SourceFile": "n/a",
      "SelectorTraceFile": "n/a",
      "FamilyId": "n/a",
      "Signature": "n/a",
      "SelectionSource": "n/a",
      "OwnerAddress": null,
      "ContainerAddress": null,
      "SelectedSourceAddress": null,
      "StateRecordAddress": null,
      "SelectedEntryAddress": null,
      "SourceObjectAddress": null,
      "Warnings": [
        "no selected source or source object anchor found"
      ]
    },
    {
      "FileName": "player-stat-hub-graph.json",
      "Mode": "player-stat-hub-graph",
      "GeneratedAtUtc": "2026-04-10T03:03:40.0000000-04:00",
      "LoadedAtUtc": null,
      "ProcessName": "n/a",
      "ProcessId": null,
      "SourceFile": "n/a",
      "SelectorTraceFile": "n/a",
      "FamilyId": "n/a",
      "Signature": "n/a",
      "SelectionSource": "n/a",
      "OwnerAddress": "0X1576A38AA10",
      "ContainerAddress": null,
      "SelectedSourceAddress": "0X1577AC2FB60",
      "StateRecordAddress": "0X1576A38AAD8",
      "SelectedEntryAddress": null,
      "SourceObjectAddress": "0X1577AC2FB60",
      "Warnings": []
    },
    {
      "FileName": "player-state-projector-trace.json",
      "Mode": "player-state-projector-trace",
      "GeneratedAtUtc": "2026-04-10T09:04:31.0000000-04:00",
      "LoadedAtUtc": null,
      "ProcessName": "n/a",
      "ProcessId": null,
      "SourceFile": "n/a",
      "SelectorTraceFile": "n/a",
      "FamilyId": "n/a",
      "Signature": "n/a",
      "SelectionSource": "n/a",
      "OwnerAddress": "0X1576A38AA10",
      "ContainerAddress": null,
      "SelectedSourceAddress": "0X1577AC2FB60",
      "StateRecordAddress": "0X1576A38AAD8",
      "SelectedEntryAddress": null,
      "SourceObjectAddress": null,
      "Warnings": []
    },
    {
      "FileName": "quick-camera-alts-test.json",
      "Mode": "quick-camera-alts-test",
      "GeneratedAtUtc": "2026-04-13T00:12:02.0000000-04:00",
      "LoadedAtUtc": null,
      "ProcessName": "n/a",
      "ProcessId": null,
      "SourceFile": "n/a",
      "SelectorTraceFile": "n/a",
      "FamilyId": "n/a",
      "Signature": "n/a",
      "SelectionSource": "n/a",
      "OwnerAddress": null,
      "ContainerAddress": null,
      "SelectedSourceAddress": null,
      "StateRecordAddress": null,
      "SelectedEntryAddress": null,
      "SourceObjectAddress": null,
      "Warnings": [
        "no selected source or source object anchor found"
      ]
    },
    {
      "FileName": "region-15788C24860-idle-after.json",
      "Mode": "n/a",
      "GeneratedAtUtc": "2026-04-11T15:31:08.0000000-04:00",
      "LoadedAtUtc": null,
      "ProcessName": "n/a",
      "ProcessId": null,
      "SourceFile": "n/a",
      "SelectorTraceFile": "n/a",
      "FamilyId": "n/a",
      "Signature": "n/a",
      "SelectionSource": "n/a",
      "OwnerAddress": null,
      "ContainerAddress": null,
      "SelectedSourceAddress": null,
      "StateRecordAddress": null,
      "SelectedEntryAddress": null,
      "SourceObjectAddress": null,
      "Warnings": [
        "no selected source or source object anchor found"
      ]
    },
    {
      "FileName": "region-15788C24860-idle-before.json",
      "Mode": "n/a",
      "GeneratedAtUtc": "2026-04-11T15:31:06.0000000-04:00",
      "LoadedAtUtc": null,
      "ProcessName": "n/a",
      "ProcessId": null,
      "SourceFile": "n/a",
      "SelectorTraceFile": "n/a",
      "FamilyId": "n/a",
      "Signature": "n/a",
      "SelectionSource": "n/a",
      "OwnerAddress": null,
      "ContainerAddress": null,
      "SelectedSourceAddress": null,
      "StateRecordAddress": null,
      "SelectedEntryAddress": null,
      "SourceObjectAddress": null,
      "Warnings": [
        "no selected source or source object anchor found"
      ]
    },
    {
      "FileName": "region-15788C24860-pitch-down-after.json",
      "Mode": "n/a",
      "GeneratedAtUtc": "2026-04-11T15:33:51.0000000-04:00",
      "LoadedAtUtc": null,
      "ProcessName": "n/a",
      "ProcessId": null,
      "SourceFile": "n/a",
      "SelectorTraceFile": "n/a",
      "FamilyId": "n/a",
      "Signature": "n/a",
      "SelectionSource": "n/a",
      "OwnerAddress": null,
      "ContainerAddress": null,
      "SelectedSourceAddress": null,
      "StateRecordAddress": null,
      "SelectedEntryAddress": null,
      "SourceObjectAddress": null,
      "Warnings": [
        "no selected source or source object anchor found"
      ]
    },
    {
      "FileName": "region-15788C24860-pitch-down-before.json",
      "Mode": "n/a",
      "GeneratedAtUtc": "2026-04-11T15:33:28.0000000-04:00",
      "LoadedAtUtc": null,
      "ProcessName": "n/a",
      "ProcessId": null,
      "SourceFile": "n/a",
      "SelectorTraceFile": "n/a",
      "FamilyId": "n/a",
      "Signature": "n/a",
      "SelectionSource": "n/a",
      "OwnerAddress": null,
      "ContainerAddress": null,
      "SelectedSourceAddress": null,
      "StateRecordAddress": null,
      "SelectedEntryAddress": null,
      "SourceObjectAddress": null,
      "Warnings": [
        "no selected source or source object anchor found"
      ]
    },
    {
      "FileName": "region-15788C24860-pitch-up-after.json",
      "Mode": "n/a",
      "GeneratedAtUtc": "2026-04-11T15:33:10.0000000-04:00",
      "LoadedAtUtc": null,
      "ProcessName": "n/a",
      "ProcessId": null,
      "SourceFile": "n/a",
      "SelectorTraceFile": "n/a",
      "FamilyId": "n/a",
      "Signature": "n/a",
      "SelectionSource": "n/a",
      "OwnerAddress": null,
      "ContainerAddress": null,
      "SelectedSourceAddress": null,
      "StateRecordAddress": null,
      "SelectedEntryAddress": null,
      "SourceObjectAddress": null,
      "Warnings": [
        "no selected source or source object anchor found"
      ]
    },
    {
      "FileName": "region-15788C24860-pitch-up-before.json",
      "Mode": "n/a",
      "GeneratedAtUtc": "2026-04-11T15:32:47.0000000-04:00",
      "LoadedAtUtc": null,
      "ProcessName": "n/a",
      "ProcessId": null,
      "SourceFile": "n/a",
      "SelectorTraceFile": "n/a",
      "FamilyId": "n/a",
      "Signature": "n/a",
      "SelectionSource": "n/a",
      "OwnerAddress": null,
      "ContainerAddress": null,
      "SelectedSourceAddress": null,
      "StateRecordAddress": null,
      "SelectedEntryAddress": null,
      "SourceObjectAddress": null,
      "Warnings": [
        "no selected source or source object anchor found"
      ]
    },
    {
      "FileName": "region-15788C24860-yaw-left-after.json",
      "Mode": "n/a",
      "GeneratedAtUtc": "2026-04-11T15:32:36.0000000-04:00",
      "LoadedAtUtc": null,
      "ProcessName": "n/a",
      "ProcessId": null,
      "SourceFile": "n/a",
      "SelectorTraceFile": "n/a",
      "FamilyId": "n/a",
      "Signature": "n/a",
      "SelectionSource": "n/a",
      "OwnerAddress": null,
      "ContainerAddress": null,
      "SelectedSourceAddress": null,
      "StateRecordAddress": null,
      "SelectedEntryAddress": null,
      "SourceObjectAddress": null,
      "Warnings": [
        "no selected source or source object anchor found"
      ]
    },
    {
      "FileName": "region-15788C24860-yaw-left-before.json",
      "Mode": "n/a",
      "GeneratedAtUtc": "2026-04-11T15:32:11.0000000-04:00",
      "LoadedAtUtc": null,
      "ProcessName": "n/a",
      "ProcessId": null,
      "SourceFile": "n/a",
      "SelectorTraceFile": "n/a",
      "FamilyId": "n/a",
      "Signature": "n/a",
      "SelectionSource": "n/a",
      "OwnerAddress": null,
      "ContainerAddress": null,
      "SelectedSourceAddress": null,
      "StateRecordAddress": null,
      "SelectedEntryAddress": null,
      "SourceObjectAddress": null,
      "Warnings": [
        "no selected source or source object anchor found"
      ]
    },
    {
      "FileName": "region-15788C24860-yaw-right-after.json",
      "Mode": "n/a",
      "GeneratedAtUtc": "2026-04-11T15:31:50.0000000-04:00",
      "LoadedAtUtc": null,
      "ProcessName": "n/a",
      "ProcessId": null,
      "SourceFile": "n/a",
      "SelectorTraceFile": "n/a",
      "FamilyId": "n/a",
      "Signature": "n/a",
      "SelectionSource": "n/a",
      "OwnerAddress": null,
      "ContainerAddress": null,
      "SelectedSourceAddress": null,
      "StateRecordAddress": null,
      "SelectedEntryAddress": null,
      "SourceObjectAddress": null,
      "Warnings": [
        "no selected source or source object anchor found"
      ]
    },
    {
      "FileName": "region-15788C24860-yaw-right-before.json",
      "Mode": "n/a",
      "GeneratedAtUtc": "2026-04-11T15:31:28.0000000-04:00",
      "LoadedAtUtc": null,
      "ProcessName": "n/a",
      "ProcessId": null,
      "SourceFile": "n/a",
      "SelectorTraceFile": "n/a",
      "FamilyId": "n/a",
      "Signature": "n/a",
      "SelectionSource": "n/a",
      "OwnerAddress": null,
      "ContainerAddress": null,
      "SelectedSourceAddress": null,
      "StateRecordAddress": null,
      "SelectedEntryAddress": null,
      "SourceObjectAddress": null,
      "Warnings": [
        "no selected source or source object anchor found"
      ]
    },
    {
      "FileName": "session-watchset.json",
      "Mode": "session-watchset",
      "GeneratedAtUtc": "2026-04-10T09:07:21.0000000-04:00",
      "LoadedAtUtc": null,
      "ProcessName": "rift_x64",
      "ProcessId": null,
      "SourceFile": "n/a",
      "SelectorTraceFile": "n/a",
      "FamilyId": "n/a",
      "Signature": "n/a",
      "SelectionSource": "n/a",
      "OwnerAddress": null,
      "ContainerAddress": null,
      "SelectedSourceAddress": "0X1577AC2FB60",
      "StateRecordAddress": null,
      "SelectedEntryAddress": null,
      "SourceObjectAddress": null,
      "Warnings": []
    },
    {
      "FileName": "walk-owner-state-pointers.json",
      "Mode": "walk-owner-state-pointers",
      "GeneratedAtUtc": "2026-04-10T12:52:06.0000000-04:00",
      "LoadedAtUtc": null,
      "ProcessName": "n/a",
      "ProcessId": null,
      "SourceFile": "n/a",
      "SelectorTraceFile": "n/a",
      "FamilyId": "n/a",
      "Signature": "n/a",
      "SelectionSource": "n/a",
      "OwnerAddress": null,
      "ContainerAddress": null,
      "SelectedSourceAddress": null,
      "StateRecordAddress": null,
      "SelectedEntryAddress": null,
      "SourceObjectAddress": null,
      "Warnings": [
        "no selected source or source object anchor found"
      ]
    }
  ],
  "SelectedSourceGroups": [
    {
      "Address": "0X1577AC2FB60",
      "Count": 15,
      "Files": [
        "camera-alts-stimulus-safe.json",
        "camera-alts-stimulus.json",
        "camera-altz-stimulus-safe.json",
        "camera-altz-stimulus.json",
        "ce-family-neighborhood.json",
        "owner-state-neighborhood.json",
        "player-coord-trace-cluster.json",
        "player-coord-write-trace.json",
        "player-owner-components.json",
        "player-owner-graph.json",
        "player-source-accessor-family.json",
        "player-source-chain.json",
        "player-stat-hub-graph.json",
        "player-state-projector-trace.json",
        "session-watchset.json"
      ]
    },
    {
      "Address": "0X2E199183210",
      "Count": 1,
      "Files": [
        "player-selector-owner-trace.json"
      ]
    }
  ],
  "OwnerGroups": [
    {
      "Address": "0X1576A38AA10",
      "Count": 9,
      "Files": [
        "camera-alts-stimulus-safe.json",
        "camera-alts-stimulus.json",
        "camera-altz-stimulus-safe.json",
        "camera-altz-stimulus.json",
        "owner-state-neighborhood.json",
        "player-owner-components.json",
        "player-owner-graph.json",
        "player-stat-hub-graph.json",
        "player-state-projector-trace.json"
      ]
    },
    {
      "Address": "0X2E19901B210",
      "Count": 1,
      "Files": [
        "player-selector-owner-trace.json"
      ]
    }
  ],
  "Warnings": [
    "actor-orientation-key-profile.json: no selected source or source object anchor found",
    "auto-camera-alts-diff.json: no selected source or source object anchor found",
    "camera-yaw-candidates.json: no selected source or source object anchor found",
    "ce-smart-player-family.json: no selected source or source object anchor found",
    "deep-scan-entry15.json: no selected source or source object anchor found",
    "hotspot-15788C21-after-idle.json: no selected source or source object anchor found",
    "hotspot-15788C21-after-pitch.json: no selected source or source object anchor found",
    "hotspot-15788C21-after-yaw.json: no selected source or source object anchor found",
    "hotspot-15788C21-baseline.json: no selected source or source object anchor found",
    "hotspot-15788C21-before-idle.json: no selected source or source object anchor found",
    "hotspot-15788C21-before-pitch.json: no selected source or source object anchor found",
    "hotspot-15788C21-before-yaw.json: no selected source or source object anchor found",
    "manual-camera-alts-diff.json: no selected source or source object anchor found",
    "player-actor-orientation.json: no selected source or source object anchor found",
    "player-current-anchor.json: no selected source or source object anchor found",
    "player-stat-component-candidates.json: no selected source or source object anchor found",
    "quick-camera-alts-test.json: no selected source or source object anchor found",
    "region-15788C24860-idle-after.json: no selected source or source object anchor found",
    "region-15788C24860-idle-before.json: no selected source or source object anchor found",
    "region-15788C24860-pitch-down-after.json: no selected source or source object anchor found",
    "region-15788C24860-pitch-down-before.json: no selected source or source object anchor found",
    "region-15788C24860-pitch-up-after.json: no selected source or source object anchor found",
    "region-15788C24860-pitch-up-before.json: no selected source or source object anchor found",
    "region-15788C24860-yaw-left-after.json: no selected source or source object anchor found",
    "region-15788C24860-yaw-left-before.json: no selected source or source object anchor found",
    "region-15788C24860-yaw-right-after.json: no selected source or source object anchor found",
    "region-15788C24860-yaw-right-before.json: no selected source or source object anchor found",
    "walk-owner-state-pointers.json: no selected source or source object anchor found",
    "selected-source mismatch | player-selector-owner-trace.json.SelectedSourceAddress=0X2E199183210 vs player-owner-components.json.SelectedSourceAddress=0X1577AC2FB60",
    "owner-address mismatch | player-selector-owner-trace.json.OwnerAddress=0X2E19901B210 vs player-owner-components.json.OwnerAddress=0X1576A38AA10"
  ]
}
